wdb/__init__.py
wdb/__main__.py
wdb/version.py
wdb/data/__init__.py
wdb/data/desktop-build-statistics.xlsx
wdb/data/config/config.yaml
windows_desktop_builds-0.0.14.dist-info/licenses/LICENSE.md
windows_desktop_builds-0.0.14.dist-info/METADATA
windows_desktop_builds-0.0.14.dist-info/WHEEL
windows_desktop_builds-0.0.14.dist-info/entry_points.txt
windows_desktop_builds-0.0.14.dist-info/top_level.txt
windows_desktop_builds-0.0.14.dist-info/RECORD
